[
    {
        "slug": "bobo-bm4-pro-plus",
        "title": "BOBO BM4 PRO Plus Jaw-Grip Phone Mount with Vibration Damper",
        "brand": "BOBO",
        "category": "Phone Mount",
        "type": "Handlebar Mount",
        "asin": "B0D9QTZYJW",
        "rating": 4.3,
        "reviews": 2100,
        "price": 1899,
        "affiliate_url": "https://www.amazon.in/dp/B0D9QTZYJW?tag=0x23uyx-21",
        "image": "images/products/bobo-bm4-pro-plus.jpg",
        "compatible_bikes": ["*"],
        "pros": ["PRO+ vibration damper protects phone camera", "Jaw-grip holds phone securely", "Waterproof design", "1 year warranty"],
        "cons": ["Vibration damper adds bulk", "Slightly expensive"],
        "editor_rating": 8.5,
        "best_for": "Riders wanting secure phone mounting with camera vibration protection",
        "verdict": "The BOBO BM4 PRO Plus is the best phone mount for riders who want secure jaw-grip holding with vibration dampening to protect phone cameras."
    },
    {
        "slug": "bobo-bm14-pro-plus",
        "title": "BOBO BM14 PRO Plus Quick Release Phone Mount with Vibration Damper",
        "brand": "BOBO",
        "category": "Phone Mount",
        "type": "Handlebar Mount",
        "asin": "B0D9QR37RC",
        "rating": 4.4,
        "reviews": 1800,
        "price": 1999,
        "affiliate_url": "https://www.amazon.in/dp/B0D9QR37RC?tag=0x23uyx-21",
        "image": "images/products/bobo-bm14-pro-plus.jpg",
        "compatible_bikes": ["*"],
        "pros": ["Quick-release mechanism", "PRO+ vibration damper", "Waterproof", "Fits 4-7 inch phones"],
        "cons": ["Quick release can feel loose on rough roads", "Premium pricing"],
        "editor_rating": 8.3,
        "best_for": "Riders wanting quick phone attach/detach with vibration protection",
        "verdict": "The BOBO BM14 PRO Plus offers the convenience of quick-release with the same excellent vibration dampening as the BM4 PRO Plus."
    },
    {
        "slug": "xiaomi-air-compressor-1s",
        "title": "Xiaomi Portable Electric Air Compressor 1S",
        "brand": "Xiaomi",
        "category": "Tyre Inflator",
        "type": "Portable",
        "asin": "B09V334S4L",
        "rating": 4.1,
        "reviews": 15000,
        "price": 1999,
        "affiliate_url": "https://www.amazon.in/dp/B09V334S4L?tag=0x23uyx-21",
        "image": "images/products/xiaomi-air-compressor-1s.jpg",
        "compatible_bikes": ["*"],
        "pros": ["Compact and lightweight (200g)", "Type-C charging", "5 preset modes", "LED light with SOS", "Auto shut-off"],
        "cons": ["2000mAh battery limits car tyre inflation", "No 12V car adapter included"],
        "editor_rating": 8.0,
        "best_for": "Riders wanting a compact, portable tyre inflator for motorcycle use",
        "verdict": "The Xiaomi Portable Air Compressor 1S is the most compact and lightweight tyre inflator, perfect for motorcycle riders to carry on every ride."
    },
    {
        "slug": "strief-ez-air-inflator",
        "title": "STRIFF EZ Air Portable Tyre Inflator 150PSI",
        "brand": "STRIFF",
        "category": "Tyre Inflator",
        "type": "Portable",
        "asin": "B0DYZQ458Q",
        "rating": 4.2,
        "reviews": 3500,
        "price": 1679,
        "affiliate_url": "https://www.amazon.in/dp/B0DYZQ458Q?tag=0x23uyx-21",
        "image": "images/products/strief-ez-air-inflator.jpg",
        "compatible_bikes": ["*"],
        "pros": ["4000mAh battery", "150 PSI max pressure", "Type-C charging", "5 preset modes", "Digital display"],
        "cons": ["Heavier than Xiaomi", "Basic build quality"],
        "editor_rating": 7.5,
        "best_for": "Budget riders wanting a capable portable tyre inflator",
        "verdict": "The STRIFF EZ Air offers good value with a larger 4000mAh battery and 150PSI capacity at a budget-friendly price."
    }
]
